oasis/__init__.py
oasis/clock/__init__.py
oasis/clock/clock.py
oasis/environment/__init__.py
oasis/environment/env.py
oasis/environment/env_action.py
oasis/environment/make.py
oasis/social_agent/__init__.py
oasis/social_agent/agent.py
oasis/social_agent/agent_action.py
oasis/social_agent/agent_environment.py
oasis/social_agent/agent_graph.py
oasis/social_agent/agents_generator.py
oasis/social_platform/__init__.py
oasis/social_platform/channel.py
oasis/social_platform/config/__init__.py
oasis/social_platform/config/neo4j.py
oasis/social_platform/config/user.py
oasis/social_platform/database.py
oasis/social_platform/platform.py
oasis/social_platform/platform_utils.py
oasis/social_platform/process_recsys_posts.py
oasis/social_platform/recsys.py
oasis/social_platform/schema/chat_group.sql
oasis/social_platform/schema/comment.sql
oasis/social_platform/schema/comment_dislike.sql
oasis/social_platform/schema/comment_like.sql
oasis/social_platform/schema/dislike.sql
oasis/social_platform/schema/follow.sql
oasis/social_platform/schema/group_member.sql
oasis/social_platform/schema/group_message.sql
oasis/social_platform/schema/like.sql
oasis/social_platform/schema/mute.sql
oasis/social_platform/schema/post.sql
oasis/social_platform/schema/product.sql
oasis/social_platform/schema/rec.sql
oasis/social_platform/schema/report.sql
oasis/social_platform/schema/trace.sql
oasis/social_platform/schema/user.sql
oasis/social_platform/typing.py
oasis/testing/__init__.py
oasis/testing/show_db.py
camel_oasis-0.2.5.dist-info/METADATA
camel_oasis-0.2.5.dist-info/WHEEL
camel_oasis-0.2.5.dist-info/licenses/LICENSE
camel_oasis-0.2.5.dist-info/licenses/LICENSES/license_template.txt
camel_oasis-0.2.5.dist-info/licenses/LICENSES/update_license.py
camel_oasis-0.2.5.dist-info/RECORD
